source/__init__.py
source/cli.py
source/aws/__init__.py
source/aws/cloudformation.py
source/aws/ec2.py
source/aws/eks.py
source/aws/lambda_client.py
source/aws/sam.py
source/aws/ssm.py
source/cloudformation/launch-template.yml
source/cloudformation/template.yml
source/commands/__init__.py
source/commands/bootstrap.py
source/commands/destroy.py
source/commands/list_clusters.py
source/commands/list_instances.py
source/commands/offboard.py
source/commands/onboard.py
source/commands/pricing.py
source/commands/rebalance.py
source/commands/refresh.py
source/commands/scale.py
source/lambda/instancerunner/index.py
source/lambda/spotter/index.py
source/lambda/spotter/instances.py
source/lambda/spotter/pricing.py
spotter_cli-1.0.3.dist-info/METADATA
spotter_cli-1.0.3.dist-info/WHEEL
spotter_cli-1.0.3.dist-info/entry_points.txt
spotter_cli-1.0.3.dist-info/licenses/LICENSE
spotter_cli-1.0.3.dist-info/RECORD
