Metadata-Version: 2.4
Name: spotter-cli
Version: 1.0.3
Summary: Production-grade spot instance scheduling for EKS worker nodes
Project-URL: Repository, https://github.com/mrlikl/spotter
Project-URL: Issues, https://github.com/mrlikl/spotter/issues
Project-URL: Documentation, https://github.com/mrlikl/spotter/blob/main/README.md
Author: Spotter Authors
License: MIT License
License-File: LICENSE
Keywords: aws,cost-optimization,eks,kubernetes,spot-instances
Classifier: Intended Audience :: Developers
Classifier: Intended Audience :: System Administrators
Classifier: License :: OSI Approved :: MIT License
Classifier: Operating System :: OS Independent
Classifier: Programming Language :: Python :: 3
Classifier: Topic :: System :: Systems Administration
Classifier: Topic :: Utilities
Requires-Python: >=3.9
Requires-Dist: boto3
Requires-Dist: botocore
Requires-Dist: rich
Requires-Dist: typer
